scans2any/__init__.py
scans2any/main.py
scans2any/filters/__init__.py
scans2any/filters/combine_banner.py
scans2any/filters/empty_host.py
scans2any/filters/empty_service.py
scans2any/filters/hostname_filter.py
scans2any/filters/ip_port.py
scans2any/filters/nmap_banner.py
scans2any/filters/service_filter.py
scans2any/filters/trash_banner.py
scans2any/filters/trash_hostname.py
scans2any/filters/trash_service_name.py
scans2any/filters/use_first_entry.py
scans2any/helpers/cli.py
scans2any/helpers/file_processing.py
scans2any/helpers/infrastructure.py
scans2any/helpers/utils.py
scans2any/internal/__init__.py
scans2any/internal/config.yaml
scans2any/internal/host.py
scans2any/internal/infrastructure.py
scans2any/internal/printer.py
scans2any/internal/service.py
scans2any/internal/sorted_set.py
scans2any/parsers/__init__.py
scans2any/parsers/aquatone_parser.py
scans2any/parsers/auto_parser.py
scans2any/parsers/bloodhound_parser.py
scans2any/parsers/json_parser.py
scans2any/parsers/masscan_parser.py
scans2any/parsers/merge_file_parser.py
scans2any/parsers/nessus_parser.py
scans2any/parsers/nmap_parser.py
scans2any/parsers/nxc_parser.py
scans2any/parsers/txt_parser.py
scans2any/writers/__init__.py
scans2any/writers/aquatone_writer.py
scans2any/writers/csv_writer.py
scans2any/writers/dataframe_creator.py
scans2any/writers/excel_writer.py
scans2any/writers/host_writer.py
scans2any/writers/html_writer.py
scans2any/writers/json_writer.py
scans2any/writers/latex_writer.py
scans2any/writers/markdown_writer.py
scans2any/writers/nmap_writer.py
scans2any/writers/terminal_writer.py
scans2any/writers/typst_writer.py
scans2any/writers/url_writer.py
scans2any/writers/xml_writer.py
scans2any/writers/yaml_writer.py
scans2any-0.8.1.dist-info/METADATA
scans2any-0.8.1.dist-info/WHEEL
scans2any-0.8.1.dist-info/entry_points.txt
scans2any-0.8.1.dist-info/licenses/LICENSE
scans2any-0.8.1.dist-info/RECORD
