Metadata-Version: 2.4
Name: scans2any
Version: 0.8.1
Summary: Convert infrastructure scans into various output formats such as Markdown tables, YAML, HTML, CSV, and more
Project-URL: Homepage, https://www.softscheck.com
Project-URL: Repository, https://github.com/softScheck/scans2any
Author-email: softScheck <info@softscheck.com>
License-Expression: AGPL-3.0-or-later
License-File: LICENSE
Keywords: infrastructure,pentesting,report,security
Classifier: Environment :: Console
Classifier: Framework :: Pytest
Classifier: License :: OSI Approved :: GNU Affero General Public License v3 or later (AGPLv3+)
Classifier: Operating System :: OS Independent
Classifier: Programming Language :: Python
Classifier: Topic :: Security
Classifier: Topic :: Text Processing
Requires-Python: >=3.12
Requires-Dist: defusedxml>=0.7.1
Requires-Dist: jinja2>=3.1.5
Requires-Dist: openpyxl>=3.1.5
Requires-Dist: pandas>=2.2.2
Requires-Dist: partial-json-parser>=0.2.1.1.post4
Requires-Dist: python-libnmap>=0.7.3
Requires-Dist: pyyaml>=6.0.2
Requires-Dist: sortedcontainers>=2.4.0
Requires-Dist: tabulate>=0.9.0
Requires-Dist: tqdm
Requires-Dist: wcwidth>=0.2.13
